lant/__init__.py
lant/__main__.py
lant/_version.py
lant/py.typed
lant-0.0.2.dist-info/LICENSE.txt
lant-0.0.2.dist-info/METADATA
lant-0.0.2.dist-info/WHEEL
lant-0.0.2.dist-info/entry_points.txt
lant-0.0.2.dist-info/top_level.txt
lant-0.0.2.dist-info/RECORD
