Metadata-Version: 2.1
Name: lant
Version: 0.0.2
Summary: Implements Langton\'s ant in Python
Home-page: https://github.com/jacanchaplais/lant
Author: Jacan Chaplais
Author-email: jacanchaplais@gmail.com
License: BSD 3-Clause License
Platform: unix
Platform: linux
Platform: osx
Platform: cygwin
Platform: win32
Classifier: Programming Language :: Python :: 3.8
Classifier: Programming Language :: Python :: 3.9
Classifier: Programming Language :: Python :: 3.10
Classifier: Programming Language :: Python :: 3
Classifier: License :: OSI Approved :: BSD License
Classifier: Operating System :: OS Independent
Requires-Python: >=3.8
License-File: LICENSE.txt
Requires-Dist: click (==8.1.1)
Requires-Dist: tqdm (==4.64.0)
Requires-Dist: numpy (==1.23.2)
Requires-Dist: opencv-python (==4.6.0.66)
Provides-Extra: dev
Requires-Dist: pre-commit (==2.19.0) ; extra == 'dev'
Requires-Dist: flake8 (==3.9.2) ; extra == 'dev'
Requires-Dist: tox (==3.24.3) ; extra == 'dev'
Requires-Dist: pytest (==6.2.5) ; extra == 'dev'
Requires-Dist: pytest-cov (==2.12.1) ; extra == 'dev'
Requires-Dist: mypy (==0.910) ; extra == 'dev'
